actscene_ocr/__init__.py
actscene_ocr/actscene_ocr.py
actscene_ocr/utils/document_scanner.py
actscene_ocr/utils/resize_image.py
actscene_ocr/utils/ocr/__init__.py
actscene_ocr/utils/ocr/draw.py
actscene_ocr/utils/ocr/geometry.py
actscene_ocr/utils/ocr/orientation.py
actscene_ocr/utils/ocr/pipeline.py
actscene_ocr/utils/ocr/extractors/__init__.py
actscene_ocr/utils/ocr/extractors/generic.py
actscene_ocr/utils/ocr/extractors/inin.py
actscene_ocr/utils/ocr/extractors/inkan.py
actscene_ocr/utils/ocr/extractors/jibaiseki.py
actscene_ocr/utils/ocr/extractors/jouto.py
actscene_ocr/utils/ocr/extractors/recycle.py
actscene_ocr/utils/ocr/extractors/shaken.py
actscene_ocr/utils/ocr/extractors/shaken_kiroku.py
actscene_ocr-0.1.5.dist-info/licenses/LICENSE
actscene_ocr-0.1.5.dist-info/METADATA
actscene_ocr-0.1.5.dist-info/WHEEL
actscene_ocr-0.1.5.dist-info/top_level.txt
actscene_ocr-0.1.5.dist-info/RECORD
