Metadata-Version: 2.4
Name: actscene-ocr
Version: 0.1.5
Summary: Actscene OCR: 日本語書類向けの包括的OCRパイプライン (PaddleOCRベース)
Author-email: Actscene <dev@actscene.example>
License: MIT
Keywords: OCR,PaddleOCR,Japanese,Document,actscene
Classifier: Programming Language :: Python :: 3
Classifier: License :: OSI Approved :: MIT License
Classifier: Operating System :: OS Independent
Classifier: Topic :: Scientific/Engineering :: Image Recognition
Requires-Python: >=3.10
License-File: LICENSE
Requires-Dist: setuptools>=68.0.0
Requires-Dist: wheel>=0.40.0
Requires-Dist: aiohappyeyeballs==2.6.1
Requires-Dist: aiohttp==3.12.14
Requires-Dist: aiosignal==1.4.0
Requires-Dist: annotated-types==0.7.0
Requires-Dist: anyio==4.9.0
Requires-Dist: astor==0.8.1
Requires-Dist: async-timeout==4.0.3
Requires-Dist: attrs==25.3.0
Requires-Dist: beautifulsoup4==4.13.4
Requires-Dist: cachetools==6.1.0
Requires-Dist: certifi==2025.7.14
Requires-Dist: chardet==5.2.0
Requires-Dist: charset-normalizer==3.4.2
Requires-Dist: colorlog==6.9.0
Requires-Dist: contourpy==1.3.2
Requires-Dist: cssselect==1.3.0
Requires-Dist: cssutils==2.11.1
Requires-Dist: cycler==0.12.1
Requires-Dist: dataclasses-json==0.6.7
Requires-Dist: decorator==5.2.1
Requires-Dist: distro==1.9.0
Requires-Dist: einops==0.8.1
Requires-Dist: et_xmlfile==2.0.0
Requires-Dist: exceptiongroup==1.3.0
Requires-Dist: filelock==3.18.0
Requires-Dist: fonttools==4.59.0
Requires-Dist: frozenlist==1.7.0
Requires-Dist: fsspec==2025.7.0
Requires-Dist: ftfy==6.3.1
Requires-Dist: GPUtil==1.4.0
Requires-Dist: h11==0.16.0
Requires-Dist: hf-xet==1.1.5
Requires-Dist: httpcore==1.0.9
Requires-Dist: httpx==0.28.1
Requires-Dist: httpx-sse==0.4.1
Requires-Dist: huggingface-hub==0.34.1
Requires-Dist: idna==3.10
Requires-Dist: imagesize==1.4.1
Requires-Dist: Jinja2==3.1.6
Requires-Dist: jiter==0.10.0
Requires-Dist: joblib==1.5.1
Requires-Dist: jsonpatch==1.33
Requires-Dist: jsonpointer==3.0.0
Requires-Dist: kiwisolver==1.4.8
Requires-Dist: langchain==0.3.27
Requires-Dist: langchain-community==0.3.27
Requires-Dist: langchain-core==0.3.72
Requires-Dist: langchain-openai==0.3.28
Requires-Dist: langchain-text-splitters==0.3.9
Requires-Dist: langsmith==0.4.8
Requires-Dist: lanms_neo==1.0.2
Requires-Dist: lmdb==1.7.3
Requires-Dist: lxml==6.0.0
Requires-Dist: MarkupSafe==3.0.2
Requires-Dist: marshmallow==3.26.1
Requires-Dist: matplotlib==3.10.3
Requires-Dist: more-itertools==10.7.0
Requires-Dist: multidict==6.6.3
Requires-Dist: mypy_extensions==1.1.0
Requires-Dist: networkx==3.4.2
Requires-Dist: numpy==2.2.6
Requires-Dist: openai==1.97.1
Requires-Dist: opencv-contrib-python==4.10.0.84
Requires-Dist: openpyxl==3.1.5
Requires-Dist: opt-einsum==3.3.0
Requires-Dist: orjson==3.11.1
Requires-Dist: packaging==25.0
Requires-Dist: paddleocr==3.1.1
Requires-Dist: paddlepaddle==3.1.0
Requires-Dist: paddlex==3.1.4
Requires-Dist: pandas==2.3.1
Requires-Dist: pillow==11.3.0
Requires-Dist: Polygon3==3.0.9.1
Requires-Dist: premailer==3.10.0
Requires-Dist: prettytable==3.16.0
Requires-Dist: propcache==0.3.2
Requires-Dist: protobuf==6.31.1
Requires-Dist: py-cpuinfo==9.0.0
Requires-Dist: pyclipper==1.3.0.post6
Requires-Dist: pydantic==2.11.7
Requires-Dist: pydantic-settings==2.10.1
Requires-Dist: pydantic_core==2.33.2
Requires-Dist: PyMuPDF==1.26.3
Requires-Dist: pyparsing==3.2.3
Requires-Dist: pypdfium2==4.30.0
Requires-Dist: python-dateutil==2.9.0.post0
Requires-Dist: python-docx==1.2.0
Requires-Dist: python-dotenv==1.1.1
Requires-Dist: pytz==2025.2
Requires-Dist: PyYAML==6.0.2
Requires-Dist: RapidFuzz==3.13.0
Requires-Dist: rarfile==4.2
Requires-Dist: regex==2024.11.6
Requires-Dist: requests==2.32.4
Requires-Dist: requests-toolbelt==1.0.0
Requires-Dist: ruamel.yaml==0.18.14
Requires-Dist: ruamel.yaml.clib==0.2.12
Requires-Dist: scikit-learn==1.7.1
Requires-Dist: scipy==1.15.3
Requires-Dist: shapely==2.1.1
Requires-Dist: six==1.17.0
Requires-Dist: sniffio==1.3.1
Requires-Dist: soupsieve==2.7
Requires-Dist: SQLAlchemy==2.0.41
Requires-Dist: tenacity==9.1.2
Requires-Dist: termcolor==3.1.0
Requires-Dist: threadpoolctl==3.6.0
Requires-Dist: tifffile==2025.5.10
Requires-Dist: tiktoken==0.9.0
Requires-Dist: tokenizers==0.21.2
Requires-Dist: tqdm==4.67.1
Requires-Dist: typing-inspect==0.9.0
Requires-Dist: typing-inspection==0.4.1
Requires-Dist: typing_extensions==4.14.1
Requires-Dist: tzdata==2025.2
Requires-Dist: ujson==5.10.0
Requires-Dist: urllib3==2.5.0
Requires-Dist: wcwidth==0.2.13
Requires-Dist: Werkzeug==3.1.3
Requires-Dist: yarl==1.20.1
Requires-Dist: zstandard==0.23.0
Dynamic: license-file
